kakeibox_core/__init__.py
kakeibox_core/entry_points/__init__.py
kakeibox_core/entry_points/adapters.py
kakeibox_core/entry_points/commands.py
kakeibox_core/use_cases/__init__.py
kakeibox_core/use_cases/strategy.py
kakeibox_core-0.9.2.dist-info/AUTHORS.rst
kakeibox_core-0.9.2.dist-info/LICENSE
kakeibox_core-0.9.2.dist-info/METADATA
kakeibox_core-0.9.2.dist-info/WHEEL
kakeibox_core-0.9.2.dist-info/top_level.txt
kakeibox_core-0.9.2.dist-info/RECORD
